cylinderize/__init__.py
cylinderize/__main__.py
cylinderize-1.0.1.dist-info/LICENSE
cylinderize-1.0.1.dist-info/METADATA
cylinderize-1.0.1.dist-info/WHEEL
cylinderize-1.0.1.dist-info/entry_points.txt
cylinderize-1.0.1.dist-info/top_level.txt
cylinderize-1.0.1.dist-info/RECORD
