Metadata-Version: 2.1
Name: cylinderize
Version: 1.0.1
Summary: Turn any file into a cylinder
Home-page: https://github.com/donno2048/cylinderize
Author: Elisha Hollander
License: MIT
Platform: UNKNOWN
Classifier: Programming Language :: Python :: 3
License-File: LICENSE
Requires-Dist: Pillow (>=8.3.2)
Requires-Dist: matplotlib (>=3.4.2)
Requires-Dist: numpy (>=1.20.3)
Requires-Dist: questionary (>=1.10.0)
